{
  "期数": "26090期",
  "14场对战信息": [
    {
      "场次": 1,
      "联赛": "欧冠",
      "主队": "维京古",
      "主队排名": "",
      "客队": "吉奥里",
      "客队排名": "",
      "比赛时间": "2026-07-08 00:00",
      "分析链接": "https://yllive-m.500.com/detail/football/1427686/analysis/zj"
    },
    {
      "场次": 2,
      "联赛": "瑞典超",
      "主队": "哥德堡",
      "主队排名": "14",
      "客队": "索尔纳",
      "客队排名": "10",
      "比赛时间": "2026-07-05 20:00",
      "分析链接": "https://yllive-m.500.com/detail/football/1362689/analysis/zj"
    },
    {
      "场次": 3,
      "联赛": "瑞典超",
      "主队": "卡尔马",
      "主队排名": "13",
      "客队": "奥尔格里特",
      "客队排名": "16",
      "比赛时间": "2026-07-05 20:00",
      "分析链接": "https://yllive-m.500.com/detail/football/1362692/analysis/zj"
    },
    {
      "场次": 4,
      "联赛": "瑞典超",
      "主队": "埃尔夫斯堡",
      "主队排名": "03",
      "客队": "哈马比",
      "客队排名": "04",
      "比赛时间": "2026-07-05 22:30",
      "分析链接": "https://yllive-m.500.com/detail/football/1362688/analysis/zj"
    },
    {
      "场次": 5,
      "联赛": "瑞典超",
      "主队": "布洛马波卡纳",
      "主队排名": "07",
      "客队": "哥德堡盖斯",
      "客队排名": "05",
      "比赛时间": "2026-07-07 01:00",
      "分析链接": "https://yllive-m.500.com/detail/football/1362686/analysis/zj"
    },
    {
      "场次": 6,
      "联赛": "瑞典超",
      "主队": "赫根",
      "主队排名": "02",
      "客队": "尤尔加登",
      "客队排名": "08",
      "比赛时间": "2026-07-07 01:00",
      "分析链接": "https://yllive-m.500.com/detail/football/1362690/analysis/zj"
    }
  ]
}