{
  "期数": "26033期",
  "预测方法": "数据驱动+交叉验证+半全场节奏（共同对手+泊松分布+状态矩阵）",
  "14场对战信息": [
    {
      "场次": 1,
      "联赛": "英超",
      "主队": "富勒姆",
      "主队排名": "10",
      "客队": "热刺",
      "客队排名": "16",
      "比赛时间": "2026-03-01 22:00",
      "历史交锋记录数": 40,
      "共同对手数": 9,
      "预测概率": {
        "富勒姆胜": "56.69%",
        "平": "16.85%",
        "热刺胜": "26.46%"
      },
      "预测详细数据": {
        "基础数据": {
          "主队": "富勒姆",
          "客队": "热刺",
          "主队比赛数": 20,
          "客队比赛数": 20,
          "共同对手数": 9
        },
        "攻防效率": {
          "主队进攻效率": 1.6,
          "主队防守效率": 1.55,
          "客队进攻效率": 1.4,
          "客队防守效率": 1.7,
          "主队主场进攻": 1.889,
          "客队客场进攻": 1.333
        },
        "半全场节奏": {
          "主队上半场进攻": 0.5,
          "主队下半场进攻": 1.1,
          "客队上半场进攻": 0.55,
          "客队下半场进攻": 0.85,
          "主队半场胜率": 0.269,
          "客队半场胜率": 0.269
        },
        "共同对手分析": {
          "实力对比分数": 0.633,
          "主队相对优势": "13.3%"
        },
        "预期进球": {
          "主队预期进球": 3.08,
          "客队预期进球": 1.729
        },
        "计算过程": {
          "泊松分布胜率": 0.6187,
          "泊松分布平率": 0.1749,
          "泊松分布负率": 0.2064,
          "状态矩阵概率": {
            "主队胜": 0.412,
            "平": 0.1761,
            "客队胜": 0.412
          },
          "权重分配": {
            "泊松分布权重": 0.7,
            "状态矩阵权重": 0.3
          },
          "半场效率调整因子": {
            "主队": 1.06,
            "客队": 1.027
          }
        },
        "最终预测概率": {
          "富勒姆胜": 0.5669,
          "平": 0.1685,
          "热刺胜": 0.2646
        }
      }
    },
    {
      "场次": 2,
      "联赛": "英超",
      "主队": "曼联",
      "主队排名": "04",
      "客队": "水晶宫",
      "客队排名": "13",
      "比赛时间": "2026-03-01 22:00",
      "历史交锋记录数": 40,
      "共同对手数": 11,
      "预测概率": {
        "曼联胜": "56.67%",
        "平": "22.45%",
        "水晶宫胜": "20.89%"
      },
      "预测详细数据": {
        "基础数据": {
          "主队": "曼联",
          "客队": "水晶宫",
          "主队比赛数": 20,
          "客队比赛数": 20,
          "共同对手数": 11
        },
        "攻防效率": {
          "主队进攻效率": 1.9,
          "主队防守效率": 1.35,
          "客队进攻效率": 1.1,
          "客队防守效率": 1.35,
          "主队主场进攻": 1.9,
          "客队客场进攻": 1.182
        },
        "半全场节奏": {
          "主队上半场进攻": 0.65,
          "主队下半场进攻": 1.25,
          "客队上半场进攻": 0.65,
          "客队下半场进攻": 0.45,
          "主队半场胜率": 0.346,
          "客队半场胜率": 0.307
        },
        "共同对手分析": {
          "实力对比分数": 0.612,
          "主队相对优势": "11.2%"
        },
        "预期进球": {
          "主队预期进球": 2.748,
          "客队预期进球": 1.375
        },
        "计算过程": {
          "泊松分布胜率": 0.6436,
          "泊松分布平率": 0.1773,
          "泊松分布负率": 0.1791,
          "状态矩阵概率": {
            "主队胜": 0.344,
            "平": 0.3511,
            "客队胜": 0.3049
          },
          "权重分配": {
            "泊松分布权重": 0.7,
            "状态矩阵权重": 0.3
          },
          "半场效率调整因子": {
            "主队": 1.046,
            "客队": 0.985
          }
        },
        "最终预测概率": {
          "曼联胜": 0.5667,
          "平": 0.2245,
          "水晶宫胜": 0.2089
        }
      }
    },
    {
      "场次": 3,
      "联赛": "英超",
      "主队": "阿森纳",
      "主队排名": "01",
      "客队": "切尔西",
      "客队排名": "05",
      "比赛时间": "2026-03-02 00:30",
      "历史交锋记录数": 40,
      "共同对手数": 7,
      "预测概率": {
        "阿森纳胜": "51.10%",
        "平": "19.89%",
        "切尔西胜": "29.01%"
      },
      "预测详细数据": {
        "基础数据": {
          "主队": "阿森纳",
          "客队": "切尔西",
          "主队比赛数": 20,
          "客队比赛数": 20,
          "共同对手数": 7
        },
        "攻防效率": {
          "主队进攻效率": 2.35,
          "主队防守效率": 0.95,
          "客队进攻效率": 2.1,
          "客队防守效率": 1.3,
          "主队主场进攻": 2.2,
          "客队客场进攻": 2.364
        },
        "半全场节奏": {
          "主队上半场进攻": 1.05,
          "主队下半场进攻": 1.3,
          "客队上半场进攻": 0.8,
          "客队下半场进攻": 1.3,
          "主队半场胜率": 0.463,
          "客队半场胜率": 0.463
        },
        "共同对手分析": {
          "实力对比分数": 0.535,
          "主队相对优势": "3.5%"
        },
        "预期进球": {
          "主队预期进球": 2.937,
          "客队预期进球": 1.928
        },
        "计算过程": {
          "泊松分布胜率": 0.5619,
          "泊松分布平率": 0.1858,
          "泊松分布负率": 0.2522,
          "状态矩阵概率": {
            "主队胜": 0.3974,
            "平": 0.2392,
            "客队胜": 0.3634
          },
          "权重分配": {
            "泊松分布权重": 0.7,
            "状态矩阵权重": 0.3
          },
          "半场效率调整因子": {
            "主队": 1.012,
            "客队": 1.031
          }
        },
        "最终预测概率": {
          "阿森纳胜": 0.511,
          "平": 0.1989,
          "切尔西胜": 0.2901
        }
      }
    },
    {
      "场次": 4,
      "联赛": "德甲",
      "主队": "斯图加特",
      "主队排名": "04",
      "客队": "沃尔夫斯堡",
      "客队排名": "15",
      "比赛时间": "2026-03-01 22:30",
      "历史交锋记录数": 40,
      "共同对手数": 13,
      "预测概率": {
        "斯图加特胜": "58.76%",
        "平": "17.29%",
        "沃尔夫斯堡胜": "23.95%"
      },
      "预测详细数据": {
        "基础数据": {
          "主队": "斯图加特",
          "客队": "沃尔夫斯堡",
          "主队比赛数": 20,
          "客队比赛数": 20,
          "共同对手数": 13
        },
        "攻防效率": {
          "主队进攻效率": 2.15,
          "主队防守效率": 1.3,
          "客队进攻效率": 1.3,
          "客队防守效率": 2.15,
          "主队主场进攻": 1.8,
          "客队客场进攻": 1.25
        },
        "半全场节奏": {
          "主队上半场进攻": 1.05,
          "主队下半场进攻": 1.1,
          "客队上半场进攻": 0.7,
          "客队下半场进攻": 0.6,
          "主队半场胜率": 0.463,
          "客队半场胜率": 0.307
        },
        "共同对手分析": {
          "实力对比分数": 0.63,
          "主队相对优势": "13.0%"
        },
        "预期进球": {
          "主队预期进球": 3.08,
          "客队预期进球": 1.588
        },
        "计算过程": {
          "泊松分布胜率": 0.6459,
          "泊松分布平率": 0.1697,
          "泊松分布负率": 0.1844,
          "状态矩阵概率": {
            "主队胜": 0.4463,
            "平": 0.1801,
            "客队胜": 0.3736
          },
          "权重分配": {
            "泊松分布权重": 0.7,
            "状态矩阵权重": 0.3
          },
          "半场效率调整因子": {
            "主队": 1.002,
            "客队": 0.993
          }
        },
        "最终预测概率": {
          "斯图加特胜": 0.5876,
          "平": 0.1729,
          "沃尔夫斯堡胜": 0.2395
        }
      }
    },
    {
      "场次": 5,
      "联赛": "德甲",
      "主队": "法兰克福",
      "主队排名": "08",
      "客队": "弗赖堡",
      "客队排名": "07",
      "比赛时间": "2026-03-02 00:30",
      "历史交锋记录数": 40,
      "共同对手数": 13,
      "预测概率": {
        "法兰克福胜": "50.28%",
        "平": "22.93%",
        "弗赖堡胜": "26.79%"
      },
      "预测详细数据": {
        "基础数据": {
          "主队": "法兰克福",
          "客队": "弗赖堡",
          "主队比赛数": 20,
          "客队比赛数": 20,
          "共同对手数": 13
        },
        "攻防效率": {
          "主队进攻效率": 1.4,
          "主队防守效率": 2.05,
          "客队进攻效率": 1.35,
          "客队防守效率": 1.25,
          "主队主场进攻": 1.222,
          "客队客场进攻": 0.9
        },
        "半全场节奏": {
          "主队上半场进攻": 0.55,
          "主队下半场进攻": 0.85,
          "客队上半场进攻": 0.6,
          "客队下半场进攻": 0.75,
          "主队半场胜率": 0.23,
          "客队半场胜率": 0.346
        },
        "共同对手分析": {
          "实力对比分数": 0.481,
          "主队相对优势": "-1.9%"
        },
        "预期进球": {
          "主队预期进球": 2.488,
          "客队预期进球": 1.502
        },
        "计算过程": {
          "泊松分布胜率": 0.5766,
          "泊松分布平率": 0.1951,
          "泊松分布负率": 0.2283,
          "状态矩阵概率": {
            "主队胜": 0.314,
            "平": 0.3218,
            "客队胜": 0.3642
          },
          "权重分配": {
            "泊松分布权重": 0.7,
            "状态矩阵权重": 0.3
          },
          "半场效率调整因子": {
            "主队": 1.027,
            "客队": 1.012
          }
        },
        "最终预测概率": {
          "法兰克福胜": 0.5028,
          "平": 0.2293,
          "弗赖堡胜": 0.2679
        }
      }
    },
    {
      "场次": 6,
      "联赛": "德甲",
      "主队": "汉堡",
      "主队排名": "11",
      "客队": "RB莱比锡",
      "客队排名": "05",
      "比赛时间": "2026-03-02 02:30",
      "历史交锋记录数": 40,
      "共同对手数": 15,
      "预测概率": {
        "汉堡胜": "39.60%",
        "平": "21.30%",
        "RB莱比锡胜": "39.10%"
      },
      "预测详细数据": {
        "基础数据": {
          "主队": "汉堡",
          "客队": "RB莱比锡",
          "主队比赛数": 20,
          "客队比赛数": 20,
          "共同对手数": 15
        },
        "攻防效率": {
          "主队进攻效率": 1.5,
          "主队防守效率": 1.35,
          "客队进攻效率": 2.15,
          "客队防守效率": 1.4,
          "主队主场进攻": 2.0,
          "客队客场进攻": 2.0
        },
        "半全场节奏": {
          "主队上半场进攻": 0.55,
          "主队下半场进攻": 0.95,
          "客队上半场进攻": 1.0,
          "客队下半场进攻": 1.15,
          "主队半场胜率": 0.269,
          "客队半场胜率": 0.424
        },
        "共同对手分析": {
          "实力对比分数": 0.446,
          "主队相对优势": "-5.4%"
        },
        "预期进球": {
          "主队预期进球": 2.409,
          "客队预期进球": 2.272
        },
        "计算过程": {
          "泊松分布胜率": 0.4209,
          "泊松分布平率": 0.2021,
          "泊松分布负率": 0.3769,
          "状态矩阵概率": {
            "主队胜": 0.3134,
            "平": 0.2503,
            "客队胜": 0.4363
          },
          "权重分配": {
            "泊松分布权重": 0.7,
            "状态矩阵权重": 0.3
          },
          "半场效率调整因子": {
            "主队": 1.036,
            "客队": 1.007
          }
        },
        "最终预测概率": {
          "汉堡胜": 0.396,
          "平": 0.213,
          "RB莱比锡胜": 0.391
        }
      }
    },
    {
      "场次": 7,
      "联赛": "意甲",
      "主队": "萨索洛",
      "主队排名": "09",
      "客队": "亚特兰大",
      "客队排名": "07",
      "比赛时间": "2026-03-01 22:00",
      "历史交锋记录数": 40,
      "共同对手数": 13,
      "预测概率": {
        "萨索洛胜": "27.12%",
        "平": "22.33%",
        "亚特兰大胜": "50.55%"
      },
      "预测详细数据": {
        "基础数据": {
          "主队": "萨索洛",
          "客队": "亚特兰大",
          "主队比赛数": 20,
          "客队比赛数": 20,
          "共同对手数": 13
        },
        "攻防效率": {
          "主队进攻效率": 1.2,
          "主队防守效率": 1.35,
          "客队进攻效率": 1.75,
          "客队防守效率": 0.8,
          "主队主场进攻": 1.1,
          "客队客场进攻": 0.875
        },
        "半全场节奏": {
          "主队上半场进攻": 0.55,
          "主队下半场进攻": 0.65,
          "客队上半场进攻": 0.7,
          "客队下半场进攻": 1.05,
          "主队半场胜率": 0.269,
          "客队半场胜率": 0.502
        },
        "共同对手分析": {
          "实力对比分数": 0.322,
          "主队相对优势": "-17.8%"
        },
        "预期进球": {
          "主队预期进球": 1.01,
          "客队预期进球": 1.597
        },
        "计算过程": {
          "泊松分布胜率": 0.2405,
          "泊松分布平率": 0.2519,
          "泊松分布负率": 0.5076,
          "状态矩阵概率": {
            "主队胜": 0.3482,
            "平": 0.1675,
            "客队胜": 0.4843
          },
          "权重分配": {
            "泊松分布权重": 0.7,
            "状态矩阵权重": 0.3
          },
          "半场效率调整因子": {
            "主队": 1.009,
            "客队": 1.025
          }
        },
        "最终预测概率": {
          "萨索洛胜": 0.2712,
          "平": 0.2233,
          "亚特兰大胜": 0.5055
        }
      }
    },
    {
      "场次": 8,
      "联赛": "意甲",
      "主队": "都灵",
      "主队排名": "15",
      "客队": "拉齐奥",
      "客队排名": "10",
      "比赛时间": "2026-03-02 01:00",
      "历史交锋记录数": 40,
      "共同对手数": 14,
      "预测概率": {
        "都灵胜": "25.99%",
        "平": "27.15%",
        "拉齐奥胜": "46.86%"
      },
      "预测详细数据": {
        "基础数据": {
          "主队": "都灵",
          "客队": "拉齐奥",
          "主队比赛数": 20,
          "客队比赛数": 20,
          "共同对手数": 14
        },
        "攻防效率": {
          "主队进攻效率": 1.05,
          "主队防守效率": 1.85,
          "客队进攻效率": 0.85,
          "客队防守效率": 0.95,
          "主队主场进攻": 1.111,
          "客队客场进攻": 0.6
        },
        "半全场节奏": {
          "主队上半场进攻": 0.55,
          "主队下半场进攻": 0.5,
          "客队上半场进攻": 0.15,
          "客队下半场进攻": 0.7,
          "主队半场胜率": 0.307,
          "客队半场胜率": 0.152
        },
        "共同对手分析": {
          "实力对比分数": 0.378,
          "主队相对优势": "-12.2%"
        },
        "预期进球": {
          "主队预期进球": 0.909,
          "客队预期进球": 1.356
        },
        "计算过程": {
          "泊松分布胜率": 0.2517,
          "泊松分布平率": 0.2779,
          "泊松分布负率": 0.4704,
          "状态矩阵概率": {
            "主队胜": 0.3495,
            "平": 0.3256,
            "客队胜": 0.3249
          },
          "权重分配": {
            "泊松分布权重": 0.7,
            "状态矩阵权重": 0.3
          },
          "半场效率调整因子": {
            "主队": 0.995,
            "客队": 1.182
          }
        },
        "最终预测概率": {
          "都灵胜": 0.2599,
          "平": 0.2715,
          "拉齐奥胜": 0.4686
        }
      }
    },
    {
      "场次": 9,
      "联赛": "意甲",
      "主队": "罗马",
      "主队排名": "03",
      "客队": "尤文",
      "客队排名": "05",
      "比赛时间": "2026-03-02 03:45",
      "历史交锋记录数": 40,
      "共同对手数": 8,
      "预测概率": {
        "罗马胜": "61.95%",
        "平": "15.64%",
        "尤文胜": "22.41%"
      },
      "预测详细数据": {
        "基础数据": {
          "主队": "罗马",
          "客队": "尤文",
          "主队比赛数": 20,
          "客队比赛数": 20,
          "共同对手数": 8
        },
        "攻防效率": {
          "主队进攻效率": 1.6,
          "主队防守效率": 0.8,
          "客队进攻效率": 1.85,
          "客队防守效率": 1.05,
          "主队主场进攻": 1.8,
          "客队客场进攻": 1.5
        },
        "半全场节奏": {
          "主队上半场进攻": 0.65,
          "主队下半场进攻": 0.95,
          "客队上半场进攻": 0.65,
          "客队下半场进攻": 1.2,
          "主队半场胜率": 0.385,
          "客队半场胜率": 0.385
        },
        "共同对手分析": {
          "实力对比分数": 0.543,
          "主队相对优势": "4.3%"
        },
        "预期进球": {
          "主队预期进球": 2.7,
          "客队预期进球": 1.087
        },
        "计算过程": {
          "泊松分布胜率": 0.698,
          "泊松分布平率": 0.1668,
          "泊松分布负率": 0.1352,
          "状态矩阵概率": {
            "主队胜": 0.4375,
            "平": 0.1445,
            "客队胜": 0.418
          },
          "权重分配": {
            "泊松分布权重": 0.7,
            "状态矩阵权重": 0.3
          },
          "半场效率调整因子": {
            "主队": 1.023,
            "客队": 1.042
          }
        },
        "最终预测概率": {
          "罗马胜": 0.6195,
          "平": 0.1564,
          "尤文胜": 0.2241
        }
      }
    },
    {
      "场次": 10,
      "联赛": "西甲",
      "主队": "瓦伦西亚",
      "主队排名": "16",
      "客队": "奥萨苏纳",
      "客队排名": "09",
      "比赛时间": "2026-03-01 23:15",
      "历史交锋记录数": 40,
      "共同对手数": 9,
      "预测概率": {
        "瓦伦西亚胜": "27.49%",
        "平": "22.04%",
        "奥萨苏纳胜": "50.47%"
      },
      "预测详细数据": {
        "基础数据": {
          "主队": "瓦伦西亚",
          "客队": "奥萨苏纳",
          "主队比赛数": 20,
          "客队比赛数": 20,
          "共同对手数": 9
        },
        "攻防效率": {
          "主队进攻效率": 1.35,
          "主队防守效率": 1.3,
          "客队进攻效率": 1.8,
          "客队防守效率": 1.3,
          "主队主场进攻": 1.125,
          "客队客场进攻": 1.667
        },
        "半全场节奏": {
          "主队上半场进攻": 0.3,
          "主队下半场进攻": 1.05,
          "客队上半场进攻": 0.85,
          "客队下半场进攻": 0.95,
          "主队半场胜率": 0.191,
          "客队半场胜率": 0.463
        },
        "共同对手分析": {
          "实力对比分数": 0.353,
          "主队相对优势": "-14.7%"
        },
        "预期进球": {
          "主队预期进球": 1.319,
          "客队预期进球": 2.18
        },
        "计算过程": {
          "泊松分布胜率": 0.2298,
          "泊松分布平率": 0.2091,
          "泊松分布负率": 0.5611,
          "状态矩阵概率": {
            "主队胜": 0.307,
            "平": 0.272,
            "客队胜": 0.421
          },
          "权重分配": {
            "泊松分布权重": 0.7,
            "状态矩阵权重": 0.3
          },
          "半场效率调整因子": {
            "主队": 1.124,
            "客队": 1.006
          }
        },
        "最终预测概率": {
          "瓦伦西亚胜": 0.2749,
          "平": 0.2204,
          "奥萨苏纳胜": 0.5047
        }
      }
    },
    {
      "场次": 11,
      "联赛": "西甲",
      "主队": "贝蒂斯",
      "主队排名": "05",
      "客队": "塞维利亚",
      "客队排名": "12",
      "比赛时间": "2026-03-02 01:30",
      "历史交锋记录数": 40,
      "共同对手数": 8,
      "预测概率": {
        "贝蒂斯胜": "56.93%",
        "平": "17.56%",
        "塞维利亚胜": "25.51%"
      },
      "预测详细数据": {
        "基础数据": {
          "主队": "贝蒂斯",
          "客队": "塞维利亚",
          "主队比赛数": 20,
          "客队比赛数": 20,
          "共同对手数": 8
        },
        "攻防效率": {
          "主队进攻效率": 1.75,
          "主队防守效率": 1.4,
          "客队进攻效率": 1.15,
          "客队防守效率": 1.55,
          "主队主场进攻": 2.0,
          "客队客场进攻": 1.182
        },
        "半全场节奏": {
          "主队上半场进攻": 0.8,
          "主队下半场进攻": 0.95,
          "客队上半场进攻": 0.55,
          "客队下半场进攻": 0.6,
          "主队半场胜率": 0.385,
          "客队半场胜率": 0.269
        },
        "共同对手分析": {
          "实力对比分数": 0.606,
          "主队相对优势": "10.6%"
        },
        "预期进球": {
          "主队预期进球": 3.08,
          "客队预期进球": 1.7
        },
        "计算过程": {
          "泊松分布胜率": 0.6242,
          "泊松分布平率": 0.1739,
          "泊松分布负率": 0.2019,
          "状态矩阵概率": {
            "主队胜": 0.4358,
            "平": 0.1832,
            "客队胜": 0.381
          },
          "权重分配": {
            "泊松分布权重": 0.7,
            "状态矩阵权重": 0.3
          },
          "半场效率调整因子": {
            "主队": 1.009,
            "客队": 1.004
          }
        },
        "最终预测概率": {
          "贝蒂斯胜": 0.5693,
          "平": 0.1756,
          "塞维利亚胜": 0.2551
        }
      }
    },
    {
      "场次": 12,
      "联赛": "西甲",
      "主队": "赫罗纳",
      "主队排名": "11",
      "客队": "塞尔塔",
      "客队排名": "06",
      "比赛时间": "2026-03-02 04:00",
      "历史交锋记录数": 40,
      "共同对手数": 9,
      "预测概率": {
        "赫罗纳胜": "41.07%",
        "平": "24.91%",
        "塞尔塔胜": "34.02%"
      },
      "预测详细数据": {
        "基础数据": {
          "主队": "赫罗纳",
          "客队": "塞尔塔",
          "主队比赛数": 20,
          "客队比赛数": 20,
          "共同对手数": 9
        },
        "攻防效率": {
          "主队进攻效率": 1.25,
          "主队防守效率": 1.35,
          "客队进攻效率": 1.45,
          "客队防守效率": 0.95,
          "主队主场进攻": 1.375,
          "客队客场进攻": 1.182
        },
        "半全场节奏": {
          "主队上半场进攻": 0.6,
          "主队下半场进攻": 0.65,
          "客队上半场进攻": 0.35,
          "客队下半场进攻": 1.1,
          "主队半场胜率": 0.424,
          "客队半场胜率": 0.307
        },
        "共同对手分析": {
          "实力对比分数": 0.553,
          "主队相对优势": "5.3%"
        },
        "预期进球": {
          "主队预期进球": 1.73,
          "客队预期进球": 1.402
        },
        "计算过程": {
          "泊松分布胜率": 0.4502,
          "泊松分布平率": 0.2366,
          "泊松分布负率": 0.3132,
          "状态矩阵概率": {
            "主队胜": 0.3618,
            "平": 0.3079,
            "客队胜": 0.3303
          },
          "权重分配": {
            "泊松分布权重": 0.7,
            "状态矩阵权重": 0.3
          },
          "半场效率调整因子": {
            "主队": 1.004,
            "客队": 1.107
          }
        },
        "最终预测概率": {
          "赫罗纳胜": 0.4107,
          "平": 0.2491,
          "塞尔塔胜": 0.3402
        }
      }
    },
    {
      "场次": 13,
      "联赛": "法甲",
      "主队": "里尔",
      "主队排名": "05",
      "客队": "南特",
      "客队排名": "17",
      "比赛时间": "2026-03-02 00:15",
      "历史交锋记录数": 40,
      "共同对手数": 7,
      "预测概率": {
        "里尔胜": "48.16%",
        "平": "19.46%",
        "南特胜": "32.37%"
      },
      "预测详细数据": {
        "基础数据": {
          "主队": "里尔",
          "客队": "南特",
          "主队比赛数": 20,
          "客队比赛数": 20,
          "共同对手数": 7
        },
        "攻防效率": {
          "主队进攻效率": 1.1,
          "主队防守效率": 1.2,
          "客队进攻效率": 1.25,
          "客队防守效率": 1.95,
          "主队主场进攻": 1.444,
          "客队客场进攻": 1.5
        },
        "半全场节奏": {
          "主队上半场进攻": 0.4,
          "主队下半场进攻": 0.7,
          "客队上半场进攻": 0.75,
          "客队下半场进攻": 0.5,
          "主队半场胜率": 0.269,
          "客队半场胜率": 0.307
        },
        "共同对手分析": {
          "实力对比分数": 0.645,
          "主队相对优势": "14.5%"
        },
        "预期进球": {
          "主队预期进球": 2.2,
          "客队预期进球": 1.67
        },
        "计算过程": {
          "泊松分布胜率": 0.4917,
          "泊松分布平率": 0.211,
          "泊松分布负率": 0.2974,
          "状态矩阵概率": {
            "主队胜": 0.419,
            "平": 0.1643,
            "客队胜": 0.4167
          },
          "权重分配": {
            "泊松分布权重": 0.7,
            "状态矩阵权重": 0.3
          },
          "半场效率调整因子": {
            "主队": 1.037,
            "客队": 0.983
          }
        },
        "最终预测概率": {
          "里尔胜": 0.4816,
          "平": 0.1946,
          "南特胜": 0.3237
        }
      }
    },
    {
      "场次": 14,
      "联赛": "法甲",
      "主队": "马赛",
      "主队排名": "04",
      "客队": "里昂",
      "客队排名": "03",
      "比赛时间": "2026-03-02 03:45",
      "历史交锋记录数": 40,
      "共同对手数": 7,
      "预测概率": {
        "马赛胜": "31.39%",
        "平": "17.40%",
        "里昂胜": "51.21%"
      },
      "预测详细数据": {
        "基础数据": {
          "主队": "马赛",
          "客队": "里昂",
          "主队比赛数": 20,
          "客队比赛数": 20,
          "共同对手数": 7
        },
        "攻防效率": {
          "主队进攻效率": 1.95,
          "主队防守效率": 1.6,
          "客队进攻效率": 2.05,
          "客队防守效率": 0.85,
          "主队主场进攻": 1.6,
          "客队客场进攻": 1.9
        },
        "半全场节奏": {
          "主队上半场进攻": 0.8,
          "主队下半场进攻": 1.15,
          "客队上半场进攻": 1.0,
          "客队下半场进攻": 1.05,
          "主队半场胜率": 0.424,
          "客队半场胜率": 0.424
        },
        "共同对手分析": {
          "实力对比分数": 0.394,
          "主队相对优势": "-10.6%"
        },
        "预期进球": {
          "主队预期进球": 1.611,
          "客队预期进球": 2.279
        },
        "计算过程": {
          "泊松分布胜率": 0.2749,
          "泊松分布平率": 0.2072,
          "泊松分布负率": 0.5179,
          "状态矩阵概率": {
            "主队胜": 0.3909,
            "平": 0.1012,
            "客队胜": 0.5079
          },
          "权重分配": {
            "泊松分布权重": 0.7,
            "状态矩阵权重": 0.3
          },
          "半场效率调整因子": {
            "主队": 1.022,
            "客队": 1.002
          }
        },
        "最终预测概率": {
          "马赛胜": 0.3139,
          "平": 0.174,
          "里昂胜": 0.5121
        }
      }
    }
  ]
}