{
  "期数": "26045期",
  "生成时间": "2026-03-17T19:11:06.157Z",
  "数据来源": {
    "基础预测文件": "result/26045期_预测概率.json",
    "高级预测文件": "result/26045期_高级预测概率.json"
  },
  "加权规则": "基础预测概率 + 高级预测概率",
  "计算结果": [
    {
      "场次": 1,
      "联赛": "欧罗巴",
      "主队": "弗赖堡",
      "客队": "亨克",
      "比赛时间": "2026-03-20 01:45",
      "基础预测概率": {
        "胜": 0.4765,
        "平": 0.06559999999999999,
        "负": 0.4579
      },
      "高级预测概率": {
        "胜": 0.4936,
        "平": 0.20920000000000002,
        "负": 0.29719999999999996
      },
      "合并概率": {
        "胜": 0.48505000000000004,
        "平": 0.13740000000000005,
        "负": 0.37755
      },
      "预测结果": 3,
      "共同对手实力分": {
        "主队总实力分": -0.994,
        "客队总实力分": 0.994,
        "主队相对实力比": -0.5,
        "客队相对实力比": 0.5,
        "共同对手数": 1
      },
      "预测详细数据": {
        "基础数据": {
          "主队": "弗赖堡",
          "客队": "亨克",
          "主队比赛数": 20,
          "客队比赛数": 20,
          "共同对手数": 0
        },
        "攻防效率": {
          "主队进攻效率": 1.1,
          "主队防守效率": 1.25,
          "客队进攻效率": 1.65,
          "客队防守效率": 1.45,
          "主队主场进攻": 1.5,
          "客队客场进攻": 1.667
        },
        "半全场节奏": {
          "主队上半场进攻": 0.45,
          "主队下半场进攻": 0.65,
          "客队上半场进攻": 0.65,
          "客队下半场进攻": 1,
          "主队半场胜率": 0.269,
          "客队半场胜率": 0.307
        },
        "共同对手分析": {
          "实力对比分数": 0.5,
          "主队相对优势": "0.0%"
        },
        "预期进球": {
          "主队预期进球": 1.967,
          "客队预期进球": 1.347
        },
        "计算过程": {
          "泊松分布胜率": 0.513,
          "泊松分布平率": 0.2228,
          "泊松分布负率": 0.2642,
          "状态矩阵概率": {
            "主队胜": 0.4428,
            "平": 0.1906,
            "客队胜": 0.3666
          },
          "权重分配": {
            "泊松分布权重": 0.7,
            "状态矩阵权重": 0.3
          },
          "半场效率调整因子": {
            "主队": 1.022,
            "客队": 1.027
          }
        },
        "最终预测概率": {
          "弗赖堡胜": 0.4936,
          "平": 0.2092,
          "亨克胜": 0.2972
        }
      }
    },
    {
      "场次": 2,
      "联赛": "欧罗巴",
      "主队": "里昂",
      "客队": "塞尔塔",
      "比赛时间": "2026-03-20 01:45",
      "基础预测概率": {
        "胜": 0.3017,
        "平": 0.4476,
        "负": 0.2507
      },
      "高级预测概率": {
        "胜": 0.5692,
        "平": 0.2141,
        "负": 0.2167
      },
      "合并概率": {
        "胜": 0.43545,
        "平": 0.33085,
        "负": 0.2337
      },
      "预测结果": 3,
      "共同对手实力分": {
        "主队总实力分": 2.806,
        "客队总实力分": 1.899,
        "主队相对实力比": 0.596,
        "客队相对实力比": 0.404,
        "共同对手数": 3
      },
      "预测详细数据": {
        "基础数据": {
          "主队": "里昂",
          "客队": "塞尔塔",
          "主队比赛数": 20,
          "客队比赛数": 20,
          "共同对手数": 2
        },
        "攻防效率": {
          "主队进攻效率": 1.8,
          "主队防守效率": 0.95,
          "客队进攻效率": 1.5,
          "客队防守效率": 1,
          "主队主场进攻": 2,
          "客队客场进攻": 1.2
        },
        "半全场节奏": {
          "主队上半场进攻": 0.85,
          "主队下半场进攻": 0.95,
          "客队上半场进攻": 0.5,
          "客队下半场进攻": 1,
          "主队半场胜率": 0.424,
          "客队半场胜率": 0.385
        },
        "共同对手分析": {
          "实力对比分数": 0.5,
          "主队相对优势": "0.0%"
        },
        "预期进球": {
          "主队预期进球": 2.296,
          "客队预期进球": 0.952
        },
        "计算过程": {
          "泊松分布胜率": 0.6657,
          "泊松分布平率": 0.1888,
          "泊松分布负率": 0.1454,
          "状态矩阵概率": {
            "主队胜": 0.3589,
            "平": 0.2828,
            "客队胜": 0.3583
          },
          "权重分配": {
            "泊松分布权重": 0.7,
            "状态矩阵权重": 0.3
          },
          "半场效率调整因子": {
            "主队": 1.006,
            "客队": 1.05
          }
        },
        "最终预测概率": {
          "里昂胜": 0.5692,
          "平": 0.2141,
          "塞尔塔胜": 0.2167
        }
      }
    },
    {
      "场次": 3,
      "联赛": "欧罗巴",
      "主队": "中日德兰",
      "客队": "诺丁汉森林",
      "比赛时间": "2026-03-20 01:45",
      "基础预测概率": {
        "胜": 0.5725,
        "平": 0.0587,
        "负": 0.3688
      },
      "高级预测概率": {
        "胜": 0.5666,
        "平": 0.2369,
        "负": 0.19649999999999998
      },
      "合并概率": {
        "胜": 0.56955,
        "平": 0.1478,
        "负": 0.28265
      },
      "预测结果": 3,
      "共同对手实力分": {
        "主队总实力分": 0.994,
        "客队总实力分": 2.743,
        "主队相对实力比": 0.266,
        "客队相对实力比": 0.734,
        "共同对手数": 2
      },
      "预测详细数据": {
        "基础数据": {
          "主队": "中日德兰",
          "客队": "诺丁汉森林",
          "主队比赛数": 20,
          "客队比赛数": 20,
          "共同对手数": 1
        },
        "攻防效率": {
          "主队进攻效率": 2.35,
          "主队防守效率": 1.3,
          "客队进攻效率": 1.1,
          "客队防守效率": 1.25,
          "主队主场进攻": 2.222,
          "客队客场进攻": 1.5
        },
        "半全场节奏": {
          "主队上半场进攻": 1.1,
          "主队下半场进攻": 1.25,
          "客队上半场进攻": 0.35,
          "客队下半场进攻": 0.75,
          "主队半场胜率": 0.424,
          "客队半场胜率": 0.191
        },
        "共同对手分析": {
          "实力对比分数": 0.333,
          "主队相对优势": "-16.7%"
        },
        "预期进球": {
          "主队预期进球": 1.956,
          "客队预期进球": 0.839
        },
        "计算过程": {
          "泊松分布胜率": 0.6302,
          "泊松分布平率": 0.2142,
          "泊松分布负率": 0.1556,
          "状态矩阵概率": {
            "主队胜": 0.4329,
            "平": 0.3013,
            "客队胜": 0.2658
          },
          "权重分配": {
            "泊松分布权重": 0.7,
            "状态矩阵权重": 0.3
          },
          "半场效率调整因子": {
            "主队": 1.007,
            "客队": 1.057
          }
        },
        "最终预测概率": {
          "中日德兰胜": 0.5666,
          "平": 0.2369,
          "诺丁汉森林胜": 0.1965
        }
      }
    },
    {
      "场次": 4,
      "联赛": "欧罗巴",
      "主队": "阿斯顿维拉",
      "客队": "里尔",
      "比赛时间": "2026-03-20 04:00",
      "基础预测概率": {
        "胜": 0.5442,
        "平": 0.0625,
        "负": 0.3933
      },
      "高级预测概率": {
        "胜": 0.41359999999999997,
        "平": 0.204,
        "负": 0.3824
      },
      "合并概率": {
        "胜": 0.4789,
        "平": 0.13324999999999998,
        "负": 0.38785000000000003
      },
      "预测结果": 3,
      "共同对手实力分": {
        "主队总实力分": 0.994,
        "客队总实力分": -0.994,
        "主队相对实力比": 0.5,
        "客队相对实力比": -0.5,
        "共同对手数": 1
      },
      "预测详细数据": {
        "基础数据": {
          "主队": "阿斯顿维拉",
          "客队": "里尔",
          "主队比赛数": 20,
          "客队比赛数": 20,
          "共同对手数": 0
        },
        "攻防效率": {
          "主队进攻效率": 1.3,
          "主队防守效率": 1.4,
          "客队进攻效率": 0.85,
          "客队防守效率": 1.15,
          "主队主场进攻": 1.333,
          "客队客场进攻": 1
        },
        "半全场节奏": {
          "主队上半场进攻": 0.5,
          "主队下半场进攻": 0.8,
          "客队上半场进攻": 0.3,
          "客队下半场进攻": 0.55,
          "主队半场胜率": 0.307,
          "客队半场胜率": 0.269
        },
        "共同对手分析": {
          "实力对比分数": 0.5,
          "主队相对优势": "0.0%"
        },
        "预期进球": {
          "主队预期进球": 1.629,
          "客队预期进球": 1.524
        },
        "计算过程": {
          "泊松分布胜率": 0.4026,
          "泊松分布平率": 0.2386,
          "泊松分布负率": 0.3588,
          "状态矩阵概率": {
            "主队胜": 0.4367,
            "平": 0.1423,
            "客队胜": 0.421
          },
          "权重分配": {
            "泊松分布权重": 0.7,
            "状态矩阵权重": 0.3
          },
          "半场效率调整因子": {
            "主队": 1.03,
            "客队": 1.041
          }
        },
        "最终预测概率": {
          "阿斯顿维拉胜": 0.4136,
          "平": 0.204,
          "里尔胜": 0.3824
        }
      }
    },
    {
      "场次": 5,
      "联赛": "欧罗巴",
      "主队": "波尔图",
      "客队": "斯图加特",
      "比赛时间": "2026-03-20 04:00",
      "基础预测概率": {
        "胜": 0.5442,
        "平": 0.0649,
        "负": 0.3909
      },
      "高级预测概率": {
        "胜": 0.5938,
        "平": 0.17809999999999998,
        "负": 0.2281
      },
      "合并概率": {
        "胜": 0.5690000000000001,
        "平": 0.12150000000000001,
        "负": 0.30950000000000005
      },
      "预测结果": 3,
      "共同对手实力分": {
        "主队总实力分": 0.994,
        "客队总实力分": -0.994,
        "主队相对实力比": 0.5,
        "客队相对实力比": -0.5,
        "共同对手数": 1
      },
      "预测详细数据": {
        "基础数据": {
          "主队": "波尔图",
          "客队": "斯图加特",
          "主队比赛数": 20,
          "客队比赛数": 20,
          "共同对手数": 0
        },
        "攻防效率": {
          "主队进攻效率": 1.9,
          "主队防守效率": 0.65,
          "客队进攻效率": 2.2,
          "客队防守效率": 1.1,
          "主队主场进攻": 2.364,
          "客队客场进攻": 2.667
        },
        "半全场节奏": {
          "主队上半场进攻": 0.95,
          "主队下半场进攻": 0.95,
          "客队上半场进攻": 1.1,
          "客队下半场进攻": 1.1,
          "主队半场胜率": 0.54,
          "客队半场胜率": 0.424
        },
        "共同对手分析": {
          "实力对比分数": 0.5,
          "主队相对优势": "0.0%"
        },
        "预期进球": {
          "主队预期进球": 2.938,
          "客队预期进球": 1.444
        },
        "计算过程": {
          "泊松分布胜率": 0.656,
          "泊松分布平率": 0.1703,
          "泊松分布负率": 0.1737,
          "状态矩阵概率": {
            "主队胜": 0.4487,
            "平": 0.1962,
            "客队胜": 0.3551
          },
          "权重分配": {
            "泊松分布权重": 0.7,
            "状态矩阵权重": 0.3
          },
          "半场效率调整因子": {
            "主队": 1,
            "客队": 1
          }
        },
        "最终预测概率": {
          "波尔图胜": 0.5938,
          "平": 0.1781,
          "斯图加特胜": 0.2281
        }
      }
    },
    {
      "场次": 6,
      "联赛": "欧罗巴",
      "主队": "贝蒂斯",
      "客队": "帕纳辛纳科斯",
      "比赛时间": "2026-03-20 04:00",
      "基础预测概率": {
        "胜": 0.4765,
        "平": 0.06559999999999999,
        "负": 0.4579
      },
      "高级预测概率": {
        "胜": 0.49439999999999995,
        "平": 0.2266,
        "负": 0.27899999999999997
      },
      "合并概率": {
        "胜": 0.48545,
        "平": 0.14610000000000004,
        "负": 0.36845
      },
      "预测结果": 3,
      "共同对手实力分": {
        "主队总实力分": -2.843,
        "客队总实力分": -0.911,
        "主队相对实力比": -0.757,
        "客队相对实力比": -0.243,
        "共同对手数": 2
      },
      "预测详细数据": {
        "基础数据": {
          "主队": "贝蒂斯",
          "客队": "帕纳辛纳科斯",
          "主队比赛数": 20,
          "客队比赛数": 20,
          "共同对手数": 1
        },
        "攻防效率": {
          "主队进攻效率": 1.35,
          "主队防守效率": 1.35,
          "客队进攻效率": 1.5,
          "客队防守效率": 0.9,
          "主队主场进攻": 1.778,
          "客队客场进攻": 1
        },
        "半全场节奏": {
          "主队上半场进攻": 0.7,
          "主队下半场进攻": 0.65,
          "客队上半场进攻": 0.7,
          "客队下半场进攻": 0.8,
          "主队半场胜率": 0.346,
          "客队半场胜率": 0.424
        },
        "共同对手分析": {
          "实力对比分数": 0.5,
          "主队相对优势": "0.0%"
        },
        "预期进球": {
          "主队预期进球": 2.279,
          "客队预期进球": 1.347
        },
        "计算过程": {
          "泊松分布胜率": 0.5733,
          "泊松分布平率": 0.2035,
          "泊松分布负率": 0.2232,
          "状态矩阵概率": {
            "主队胜": 0.3165,
            "平": 0.2806,
            "客队胜": 0.4029
          },
          "权重分配": {
            "泊松分布权重": 0.7,
            "状态矩阵权重": 0.3
          },
          "半场效率调整因子": {
            "主队": 0.996,
            "客队": 1.007
          }
        },
        "最终预测概率": {
          "贝蒂斯胜": 0.4944,
          "平": 0.2266,
          "帕纳辛纳科斯胜": 0.279
        }
      }
    },
    {
      "场次": 7,
      "联赛": "欧罗巴",
      "主队": "罗马",
      "客队": "博洛尼亚",
      "比赛时间": "2026-03-20 04:00",
      "基础预测概率": {
        "胜": 0.32539999999999997,
        "平": 0.3934,
        "负": 0.2812
      },
      "高级预测概率": {
        "胜": 0.5321,
        "平": 0.2023,
        "负": 0.2656
      },
      "合并概率": {
        "胜": 0.42875,
        "平": 0.29785000000000006,
        "负": 0.27340000000000003
      },
      "预测结果": 3,
      "共同对手实力分": {
        "主队总实力分": 2.42,
        "客队总实力分": -2.631,
        "主队相对实力比": 0.479,
        "客队相对实力比": -0.521,
        "共同对手数": 9
      },
      "预测详细数据": {
        "基础数据": {
          "主队": "罗马",
          "客队": "博洛尼亚",
          "主队比赛数": 20,
          "客队比赛数": 20,
          "共同对手数": 8
        },
        "攻防效率": {
          "主队进攻效率": 1.65,
          "主队防守效率": 1,
          "客队进攻效率": 1.2,
          "客队防守效率": 1.25,
          "主队主场进攻": 2.111,
          "客队客场进攻": 1.667
        },
        "半全场节奏": {
          "主队上半场进攻": 0.65,
          "主队下半场进攻": 1,
          "客队上半场进攻": 0.4,
          "客队下半场进攻": 0.8,
          "主队半场胜率": 0.385,
          "客队半场胜率": 0.307
        },
        "共同对手分析": {
          "实力对比分数": 0.516,
          "主队相对优势": "1.6%"
        },
        "预期进球": {
          "主队预期进球": 2.47,
          "客队预期进球": 1.447
        },
        "计算过程": {
          "泊松分布胜率": 0.585,
          "泊松分布平率": 0.1948,
          "泊松分布负率": 0.2202,
          "状态矩阵概率": {
            "主队胜": 0.4092,
            "平": 0.2383,
            "客队胜": 0.3524
          },
          "权重分配": {
            "泊松分布权重": 0.7,
            "状态矩阵权重": 0.3
          },
          "半场效率调整因子": {
            "主队": 1.027,
            "客队": 1.05
          }
        },
        "最终预测概率": {
          "罗马胜": 0.5321,
          "平": 0.2023,
          "博洛尼亚胜": 0.2656
        }
      }
    },
    {
      "场次": 8,
      "联赛": "欧协联",
      "主队": "雅典AEK",
      "客队": "采列",
      "比赛时间": "2026-03-20 01:45",
      "基础预测概率": {
        "胜": 0.5196999999999999,
        "平": 0.0645,
        "负": 0.4158
      },
      "高级预测概率": {
        "胜": 0.6115999999999999,
        "平": 0.185,
        "负": 0.20329999999999998
      },
      "合并概率": {
        "胜": 0.5656782839141957,
        "平": 0.12475623781189059,
        "负": 0.3095654782739137
      },
      "预测结果": 3,
      "共同对手实力分": {
        "主队总实力分": 3.977,
        "客队总实力分": -3.977,
        "主队相对实力比": 0.5,
        "客队相对实力比": -0.5,
        "共同对手数": 1
      },
      "预测详细数据": {
        "基础数据": {
          "主队": "雅典AEK",
          "客队": "采列",
          "主队比赛数": 20,
          "客队比赛数": 20,
          "共同对手数": 0
        },
        "攻防效率": {
          "主队进攻效率": 2.3,
          "主队防守效率": 0.7,
          "客队进攻效率": 1.7,
          "客队防守效率": 1.4,
          "主队主场进攻": 2.333,
          "客队客场进攻": 1.455
        },
        "半全场节奏": {
          "主队上半场进攻": 0.8,
          "主队下半场进攻": 1.5,
          "客队上半场进攻": 0.75,
          "客队下半场进攻": 0.95,
          "主队半场胜率": 0.463,
          "客队半场胜率": 0.385
        },
        "共同对手分析": {
          "实力对比分数": 0.5,
          "主队相对优势": "0.0%"
        },
        "预期进球": {
          "主队预期进球": 2.607,
          "客队预期进球": 1.056
        },
        "计算过程": {
          "泊松分布胜率": 0.6914,
          "泊松分布平率": 0.1712,
          "泊松分布负率": 0.1374,
          "状态矩阵概率": {
            "主队胜": 0.3969,
            "平": 0.2353,
            "客队胜": 0.3678
          },
          "权重分配": {
            "泊松分布权重": 0.7,
            "状态矩阵权重": 0.3
          },
          "半场效率调整因子": {
            "主队": 1.044,
            "客队": 1.013
          }
        },
        "最终预测概率": {
          "雅典AEK胜": 0.6116,
          "平": 0.185,
          "采列胜": 0.2033
        }
      }
    },
    {
      "场次": 9,
      "联赛": "欧协联",
      "主队": "AEK拉纳卡",
      "客队": "水晶宫",
      "比赛时间": "2026-03-20 01:45",
      "基础预测概率": {
        "胜": 0.33149999999999996,
        "平": 0.42450000000000004,
        "负": 0.2439
      },
      "高级预测概率": {
        "胜": 0.5262,
        "平": 0.2723,
        "负": 0.2014
      },
      "合并概率": {
        "胜": 0.4288928892889288,
        "平": 0.3484348434843485,
        "负": 0.22267226722672268
      },
      "预测结果": 3,
      "共同对手实力分": {
        "主队总实力分": 0,
        "客队总实力分": 0,
        "主队相对实力比": 0.5,
        "客队相对实力比": 0.5,
        "共同对手数": 1
      },
      "预测详细数据": {
        "基础数据": {
          "主队": "AEK拉纳卡",
          "客队": "水晶宫",
          "主队比赛数": 20,
          "客队比赛数": 20,
          "共同对手数": 0
        },
        "攻防效率": {
          "主队进攻效率": 1.5,
          "主队防守效率": 0.7,
          "客队进攻效率": 1,
          "客队防守效率": 1.3,
          "主队主场进攻": 2.111,
          "客队客场进攻": 1.1
        },
        "半全场节奏": {
          "主队上半场进攻": 0.7,
          "主队下半场进攻": 0.8,
          "客队上半场进攻": 0.6,
          "客队下半场进攻": 0.4,
          "主队半场胜率": 0.385,
          "客队半场胜率": 0.307
        },
        "共同对手分析": {
          "实力对比分数": 0.5,
          "主队相对优势": "0.0%"
        },
        "预期进球": {
          "主队预期进球": 1.747,
          "客队预期进球": 0.769
        },
        "计算过程": {
          "泊松分布胜率": 0.6036,
          "泊松分布平率": 0.2339,
          "泊松分布负率": 0.1625,
          "状态矩阵概率": {
            "主队胜": 0.3338,
            "平": 0.3624,
            "客队胜": 0.3039
          },
          "权重分配": {
            "泊松分布权重": 0.7,
            "状态矩阵权重": 0.3
          },
          "半场效率调整因子": {
            "主队": 1.007,
            "客队": 0.983
          }
        },
        "最终预测概率": {
          "AEK拉纳卡胜": 0.5262,
          "平": 0.2723,
          "水晶宫胜": 0.2014
        }
      }
    },
    {
      "场次": 10,
      "联赛": "欧协联",
      "主队": "美因茨",
      "客队": "奥洛穆茨",
      "比赛时间": "2026-03-20 01:45",
      "基础预测概率": {
        "胜": 0.3017,
        "平": 0.4476,
        "负": 0.2507
      },
      "高级预测概率": {
        "胜": 0.5467,
        "平": 0.253,
        "负": 0.2003
      },
      "合并概率": {
        "胜": 0.4242,
        "平": 0.3503,
        "负": 0.22549999999999998
      },
      "预测结果": 3,
      "共同对手实力分": {
        "主队总实力分": 0,
        "客队总实力分": -0.874,
        "主队相对实力比": 0,
        "客队相对实力比": -1,
        "共同对手数": 2
      },
      "预测详细数据": {
        "基础数据": {
          "主队": "美因茨",
          "客队": "奥洛穆茨",
          "主队比赛数": 20,
          "客队比赛数": 20,
          "共同对手数": 1
        },
        "攻防效率": {
          "主队进攻效率": 1.2,
          "主队防守效率": 1.25,
          "客队进攻效率": 1.05,
          "客队防守效率": 1.25,
          "主队主场进攻": 1.444,
          "客队客场进攻": 1
        },
        "半全场节奏": {
          "主队上半场进攻": 0.55,
          "主队下半场进攻": 0.65,
          "客队上半场进攻": 0.65,
          "客队下半场进攻": 0.4,
          "主队半场胜率": 0.385,
          "客队半场胜率": 0.307
        },
        "共同对手分析": {
          "实力对比分数": 1,
          "主队相对优势": "50.0%"
        },
        "预期进球": {
          "主队预期进球": 1.882,
          "客队预期进球": 0.814
        },
        "计算过程": {
          "泊松分布胜率": 0.6213,
          "泊松分布平率": 0.2207,
          "泊松分布负率": 0.158,
          "状态矩阵概率": {
            "主队胜": 0.358,
            "平": 0.3292,
            "客队胜": 0.3128
          },
          "权重分配": {
            "泊松分布权重": 0.7,
            "状态矩阵权重": 0.3
          },
          "半场效率调整因子": {
            "主队": 1.009,
            "客队": 0.981
          }
        },
        "最终预测概率": {
          "美因茨胜": 0.5467,
          "平": 0.253,
          "奥洛穆茨胜": 0.2003
        }
      }
    },
    {
      "场次": 11,
      "联赛": "欧协联",
      "主队": "琴斯托霍瓦",
      "客队": "佛罗伦萨",
      "比赛时间": "2026-03-20 01:45",
      "基础预测概率": {
        "胜": 0.4765,
        "平": 0.06559999999999999,
        "负": 0.4579
      },
      "高级预测概率": {
        "胜": 0.5018,
        "平": 0.2314,
        "负": 0.2669
      },
      "合并概率": {
        "胜": 0.4891255437228139,
        "平": 0.14849257537123145,
        "负": 0.36238188090595475
      },
      "预测结果": 3,
      "共同对手实力分": {
        "主队总实力分": -0.994,
        "客队总实力分": 0.994,
        "主队相对实力比": -0.5,
        "客队相对实力比": 0.5,
        "共同对手数": 1
      },
      "预测详细数据": {
        "基础数据": {
          "主队": "琴斯托霍瓦",
          "客队": "佛罗伦萨",
          "主队比赛数": 20,
          "客队比赛数": 20,
          "共同对手数": 0
        },
        "攻防效率": {
          "主队进攻效率": 1.4,
          "主队防守效率": 1.05,
          "客队进攻效率": 1.45,
          "客队防守效率": 1.35,
          "主队主场进攻": 1.273,
          "客队客场进攻": 1.556
        },
        "半全场节奏": {
          "主队上半场进攻": 0.75,
          "主队下半场进攻": 0.65,
          "客队上半场进攻": 0.5,
          "客队下半场进攻": 0.95,
          "主队半场胜率": 0.385,
          "客队半场胜率": 0.269
        },
        "共同对手分析": {
          "实力对比分数": 0.5,
          "主队相对优势": "0.0%"
        },
        "预期进球": {
          "主队预期进球": 1.841,
          "客队预期进球": 1.072
        },
        "计算过程": {
          "泊松分布胜率": 0.549,
          "泊松分布平率": 0.2303,
          "泊松分布负率": 0.2207,
          "状态矩阵概率": {
            "主队胜": 0.4166,
            "平": 0.2401,
            "客队胜": 0.3434
          },
          "权重分配": {
            "泊松分布权重": 0.7,
            "状态矩阵权重": 0.3
          },
          "半场效率调整因子": {
            "主队": 0.993,
            "客队": 1.045
          }
        },
        "最终预测概率": {
          "琴斯托霍瓦胜": 0.5018,
          "平": 0.2314,
          "佛罗伦萨胜": 0.2669
        }
      }
    },
    {
      "场次": 12,
      "联赛": "欧协联",
      "主队": "布拉格斯巴达",
      "客队": "阿尔克马尔",
      "比赛时间": "2026-03-20 04:00",
      "基础预测概率": {
        "胜": 0.4765,
        "平": 0.06559999999999999,
        "负": 0.4579
      },
      "高级预测概率": {
        "胜": 0.5437,
        "平": 0.1815,
        "负": 0.2748
      },
      "合并概率": {
        "胜": 0.5101,
        "平": 0.12355,
        "负": 0.36634999999999995
      },
      "预测结果": 3,
      "共同对手实力分": {
        "主队总实力分": -0.994,
        "客队总实力分": 0.994,
        "主队相对实力比": -0.5,
        "客队相对实力比": 0.5,
        "共同对手数": 1
      },
      "预测详细数据": {
        "基础数据": {
          "主队": "布拉格斯巴达",
          "客队": "阿尔克马尔",
          "主队比赛数": 20,
          "客队比赛数": 20,
          "共同对手数": 0
        },
        "攻防效率": {
          "主队进攻效率": 2.05,
          "主队防守效率": 1.1,
          "客队进攻效率": 1.85,
          "客队防守效率": 1.1,
          "主队主场进攻": 3.143,
          "客队客场进攻": 1.375
        },
        "半全场节奏": {
          "主队上半场进攻": 0.9,
          "主队下半场进攻": 1.15,
          "客队上半场进攻": 0.75,
          "客队下半场进攻": 1.1,
          "主队半场胜率": 0.424,
          "客队半场胜率": 0.346
        },
        "共同对手分析": {
          "实力对比分数": 0.5,
          "主队相对优势": "0.0%"
        },
        "预期进球": {
          "主队预期进球": 3.08,
          "客队预期进球": 1.851
        },
        "计算过程": {
          "泊松分布胜率": 0.5956,
          "泊松分布平率": 0.1789,
          "泊松分布负率": 0.2256,
          "状态矩阵概率": {
            "主队胜": 0.4227,
            "平": 0.196,
            "客队胜": 0.3813
          },
          "权重分配": {
            "泊松分布权重": 0.7,
            "状态矩阵权重": 0.3
          },
          "半场效率调整因子": {
            "主队": 1.014,
            "客队": 1.023
          }
        },
        "最终预测概率": {
          "布拉格斯巴达胜": 0.5437,
          "平": 0.1815,
          "阿尔克马尔胜": 0.2748
        }
      }
    },
    {
      "场次": 13,
      "联赛": "欧协联",
      "主队": "斯特拉斯堡",
      "客队": "里耶卡",
      "比赛时间": "2026-03-20 04:00",
      "基础预测概率": {
        "胜": 0.5442,
        "平": 0.0649,
        "负": 0.3909
      },
      "高级预测概率": {
        "胜": 0.3628,
        "平": 0.2661,
        "负": 0.3711
      },
      "合并概率": {
        "胜": 0.4535,
        "平": 0.1655,
        "负": 0.381
      },
      "预测结果": 3,
      "共同对手实力分": {
        "主队总实力分": 0.994,
        "客队总实力分": -0.994,
        "主队相对实力比": 0.5,
        "客队相对实力比": -0.5,
        "共同对手数": 1
      },
      "预测详细数据": {
        "基础数据": {
          "主队": "斯特拉斯堡",
          "客队": "里耶卡",
          "主队比赛数": 20,
          "客队比赛数": 20,
          "共同对手数": 0
        },
        "攻防效率": {
          "主队进攻效率": 1.75,
          "主队防守效率": 0.95,
          "客队进攻效率": 1.55,
          "客队防守效率": 0.9,
          "主队主场进攻": 1.636,
          "客队客场进攻": 1.125
        },
        "半全场节奏": {
          "主队上半场进攻": 0.95,
          "主队下半场进攻": 0.8,
          "客队上半场进攻": 0.3,
          "客队下半场进攻": 1.25,
          "主队半场胜率": 0.502,
          "客队半场胜率": 0.23
        },
        "共同对手分析": {
          "实力对比分数": 0.5,
          "主队相对优势": "0.0%"
        },
        "预期进球": {
          "主队预期进球": 1.221,
          "客队预期进球": 1.18
        },
        "计算过程": {
          "泊松分布胜率": 0.3712,
          "泊松分布平率": 0.2773,
          "泊松分布负率": 0.3515,
          "状态矩阵概率": {
            "主队胜": 0.4138,
            "平": 0.2844,
            "客队胜": 0.3018
          },
          "权重分配": {
            "泊松分布权重": 0.7,
            "状态矩阵权重": 0.3
          },
          "半场效率调整因子": {
            "主队": 0.992,
            "客队": 1.158
          }
        },
        "最终预测概率": {
          "斯特拉斯堡胜": 0.3628,
          "平": 0.2661,
          "里耶卡胜": 0.3711
        }
      }
    },
    {
      "场次": 14,
      "联赛": "欧协联",
      "主队": "巴列卡诺",
      "客队": "萨姆松体育",
      "比赛时间": "2026-03-20 04:00",
      "基础预测概率": {
        "胜": 0.5442,
        "平": 0.0649,
        "负": 0.3909
      },
      "高级预测概率": {
        "胜": 0.5611999999999999,
        "平": 0.2137,
        "负": 0.22510000000000002
      },
      "合并概率": {
        "胜": 0.5527,
        "平": 0.1393,
        "负": 0.30800000000000005
      },
      "预测结果": 3,
      "共同对手实力分": {
        "主队总实力分": 1.989,
        "客队总实力分": -1.989,
        "主队相对实力比": 0.5,
        "客队相对实力比": -0.5,
        "共同对手数": 1
      },
      "预测详细数据": {
        "基础数据": {
          "主队": "巴列卡诺",
          "客队": "萨姆松体育",
          "主队比赛数": 20,
          "客队比赛数": 20,
          "共同对手数": 0
        },
        "攻防效率": {
          "主队进攻效率": 1.35,
          "主队防守效率": 1.25,
          "客队进攻效率": 1.25,
          "客队防守效率": 1.25,
          "主队主场进攻": 1.667,
          "客队客场进攻": 1.273
        },
        "半全场节奏": {
          "主队上半场进攻": 0.6,
          "主队下半场进攻": 0.75,
          "客队上半场进攻": 0.55,
          "客队下半场进攻": 0.7,
          "主队半场胜率": 0.346,
          "客队半场胜率": 0.269
        },
        "共同对手分析": {
          "实力对比分数": 0.5,
          "主队相对优势": "0.0%"
        },
        "预期进球": {
          "主队预期进球": 2.371,
          "客队预期进球": 1.072
        },
        "计算过程": {
          "泊松分布胜率": 0.6506,
          "泊松分布平率": 0.1885,
          "泊松分布负率": 0.1608,
          "状态矩阵概率": {
            "主队胜": 0.3479,
            "平": 0.2795,
            "客队胜": 0.3726
          },
          "权重分配": {
            "泊松分布权重": 0.7,
            "状态矩阵权重": 0.3
          },
          "半场效率调整因子": {
            "主队": 1.012,
            "客队": 1.014
          }
        },
        "最终预测概率": {
          "巴列卡诺胜": 0.5612,
          "平": 0.2137,
          "萨姆松体育胜": 0.2251
        }
      }
    }
  ]
}