{
  "期数": "26042期",
  "14场对战信息": [
    {
      "场次": 1,
      "联赛": "英超",
      "主队": "伯恩利",
      "主队排名": "19",
      "客队": "伯恩茅斯",
      "客队排名": "09",
      "比赛时间": "2026-03-14 23:00",
      "分析链接": "https://yllive-m.500.com/detail/football/1202666/analysis/zj"
    },
    {
      "场次": 2,
      "联赛": "英超",
      "主队": "切尔西",
      "主队排名": "05",
      "客队": "纽卡斯尔联",
      "客队排名": "12",
      "比赛时间": "2026-03-15 01:30",
      "分析链接": "https://yllive-m.500.com/detail/football/1202647/analysis/zj"
    },
    {
      "场次": 3,
      "联赛": "英超",
      "主队": "阿森纳",
      "主队排名": "01",
      "客队": "埃弗顿",
      "客队排名": "08",
      "比赛时间": "2026-03-15 01:30",
      "分析链接": "https://yllive-m.500.com/detail/football/1202580/analysis/zj"
    },
    {
      "场次": 4,
      "联赛": "英超",
      "主队": "西汉姆联",
      "主队排名": "18",
      "客队": "曼城",
      "客队排名": "02",
      "比赛时间": "2026-03-15 04:00",
      "分析链接": "https://yllive-m.500.com/detail/football/1202674/analysis/zj"
    },
    {
      "场次": 5,
      "联赛": "德甲",
      "主队": "多特蒙德",
      "主队排名": "02",
      "客队": "奥格斯堡",
      "客队排名": "09",
      "比赛时间": "2026-03-14 22:30",
      "分析链接": "https://yllive-m.500.com/detail/football/1206113/analysis/zj"
    },
    {
      "场次": 6,
      "联赛": "德甲",
      "主队": "勒沃库森",
      "主队排名": "06",
      "客队": "拜仁",
      "客队排名": "01",
      "比赛时间": "2026-03-14 22:30",
      "分析链接": "https://yllive-m.500.com/detail/football/1206111/analysis/zj"
    },
    {
      "场次": 7,
      "联赛": "德甲",
      "主队": "汉堡",
      "主队排名": "10",
      "客队": "科隆",
      "客队排名": "14",
      "比赛时间": "2026-03-15 01:30",
      "分析链接": "https://yllive-m.500.com/detail/football/1206116/analysis/zj"
    },
    {
      "场次": 8,
      "联赛": "意甲",
      "主队": "那不勒斯",
      "主队排名": "03",
      "客队": "莱切",
      "客队排名": "16",
      "比赛时间": "2026-03-15 01:00",
      "分析链接": "https://yllive-m.500.com/detail/football/1199632/analysis/zj"
    },
    {
      "场次": 9,
      "联赛": "意甲",
      "主队": "乌迪内斯",
      "主队排名": "11",
      "客队": "尤文",
      "客队排名": "06",
      "比赛时间": "2026-03-15 03:45",
      "分析链接": "https://yllive-m.500.com/detail/football/1199636/analysis/zj"
    },
    {
      "场次": 10,
      "联赛": "西甲",
      "主队": "马竞",
      "主队排名": "04",
      "客队": "赫塔菲",
      "客队排名": "09",
      "比赛时间": "2026-03-14 23:15",
      "分析链接": "https://yllive-m.500.com/detail/football/1215917/analysis/zj"
    },
    {
      "场次": 11,
      "联赛": "西甲",
      "主队": "皇家奥维耶多",
      "主队排名": "20",
      "客队": "瓦伦西亚",
      "客队排名": "12",
      "比赛时间": "2026-03-15 01:30",
      "分析链接": "https://yllive-m.500.com/detail/football/1215920/analysis/zj"
    },
    {
      "场次": 12,
      "联赛": "西甲",
      "主队": "皇马",
      "主队排名": "02",
      "客队": "埃尔切",
      "客队排名": "17",
      "比赛时间": "2026-03-15 04:00",
      "分析链接": "https://yllive-m.500.com/detail/football/1215922/analysis/zj"
    },
    {
      "场次": 13,
      "联赛": "法甲",
      "主队": "洛里昂",
      "主队排名": "10",
      "客队": "朗斯",
      "客队排名": "02",
      "比赛时间": "2026-03-15 00:00",
      "分析链接": "https://yllive-m.500.com/detail/football/1205676/analysis/zj"
    },
    {
      "场次": 14,
      "联赛": "法甲",
      "主队": "昂热",
      "主队排名": "11",
      "客队": "尼斯",
      "客队排名": "15",
      "比赛时间": "2026-03-15 02:00",
      "分析链接": "https://yllive-m.500.com/detail/football/1205674/analysis/zj"
    }
  ]
}